README.md
setup.py
easylabwork/__init__.py
easylabwork/easylabwork.py
easylabwork.egg-info/PKG-INFO
easylabwork.egg-info/SOURCES.txt
easylabwork.egg-info/dependency_links.txt
easylabwork.egg-info/entry_points.txt
easylabwork.egg-info/top_level.txt