Metadata-Version: 1.0
Name: easylabwork
Version: 0.7.0
Summary: Python package from making it easy to generate lab work codes
Home-page: UNKNOWN
Author: Jeremy Fix
Author-email: jeremy.fix@centralesupelec.fr
License: LICENSE
Platform: UNKNOWN
